{
  "_comment": "Topic routing for the Basecamp Intel supergroup. Set topic_id for each category once you've created the supergroup + topics. Until topic_id is set, the script posts to the chat without a thread (works for plain channels too). Run reports go to reports/<category>/YYYY-MM-DD.md; the workflow extracts <category> from the path and looks it up here.",

  "default_category": "opportunities",

  "categories": {
    "opportunities": {
      "label": "💼 Opportunities",
      "topic_id": 2,
      "has_deadline_board": true
    },
    "education": {
      "label": "📚 Education",
      "topic_id": 3,
      "has_deadline_board": false
    },
    "news": {
      "label": "📰 News",
      "topic_id": 4,
      "has_deadline_board": false
    },
    "linkedin": {
      "label": "💼 LinkedIn",
      "topic_id": null,
      "has_deadline_board": false
    }
  }
}
